quickls/__init__.py
quickls/__main__.py
quickls/ui.html
quickls-0.1.0.dist-info/METADATA
quickls-0.1.0.dist-info/WHEEL
quickls-0.1.0.dist-info/entry_points.txt
quickls-0.1.0.dist-info/top_level.txt
quickls-0.1.0.dist-info/RECORD
