Metadata-Version: 2.4
Name: quickls
Version: 0.1.0
Summary: QLS - Quick Listing Server, a prettier version of Python's http.server.
License-Expression: MIT
Requires-Python: >=3.8
